AUTHORS.rst
CONTRIBUTING.rst
HISTORY.rst
LICENSE
MANIFEST.in
README.rst
setup.cfg
setup.py
mptt_tree_view/__init__.py
mptt_tree_view/default_settings.py
mptt_tree_view/dynamic_tree_view.py
mptt_tree_view/models.py
mptt_tree_view/urls.py
mptt_tree_view/views.py
mptt_tree_view.egg-info/PKG-INFO
mptt_tree_view.egg-info/SOURCES.txt
mptt_tree_view.egg-info/dependency_links.txt
mptt_tree_view.egg-info/not-zip-safe
mptt_tree_view.egg-info/requires.txt
mptt_tree_view.egg-info/top_level.txt
mptt_tree_view/static/css/jquery-sortable-lists.css
mptt_tree_view/static/css/mptt_tree_view.css
mptt_tree_view/static/js/dynamic_jstree_list.js
mptt_tree_view/static/js/jquery_sortable_list_for_mptt_tree.js
mptt_tree_view/static/js/jstree_list.js
mptt_tree_view/static/js/mptt_ajax.js
mptt_tree_view/static/js/mptt_tree_view.js
mptt_tree_view/static/js/tree_editor.js
mptt_tree_view/templates/mptt_tree_view/base.html
mptt_tree_view/templates/mptt_tree_view/dynamic_jstree_list.html
mptt_tree_view/templates/mptt_tree_view/jquery_sortable_list.html
mptt_tree_view/templates/mptt_tree_view/jstree_list.html
mptt_tree_view/templates/mptt_tree_view/nestable_tree.html