Metadata-Version: 1.1
Name: mptt-tree-view
Version: 0.1.0
Summary: View tool for Django MPTT
Home-page: https://github.com/weijia/mptt-tree-view
Author: Richard
Author-email: richardwangwang@gmail.com
License: BSD
Keywords: mptt-tree-view
Platform: UNKNOWN
Classifier: Development Status :: 3 - Alpha
Classifier: Framework :: Django
Classifier: Framework :: Django :: 1.8
Classifier: Framework :: Django :: 1.9
Classifier: Intended Audience :: Developers
Classifier: License :: OSI Approved :: BSD License
Classifier: Natural Language :: English
Classifier: Programming Language :: Python :: 2
Classifier: Programming Language :: Python :: 2.7
Classifier: Programming Language :: Python :: 3
Classifier: Programming Language :: Python :: 3.3
Classifier: Programming Language :: Python :: 3.4
Classifier: Programming Language :: Python :: 3.5
